CHANGES.txt
README.txt
TODO.txt
bootstrap.py
buildout.cfg
debug.cfg
salesforce.cfg
setup.py
test-plone-3.x.cfg
test-plone-4.x.cfg
docs/DEVELOPING.txt
docs/LICENSE.GPL
docs/LICENSE.txt
src/collective/__init__.py
src/collective.megaphone.egg-info/PKG-INFO
src/collective.megaphone.egg-info/SOURCES.txt
src/collective.megaphone.egg-info/dependency_links.txt
src/collective.megaphone.egg-info/entry_points.txt
src/collective.megaphone.egg-info/namespace_packages.txt
src/collective.megaphone.egg-info/not-zip-safe
src/collective.megaphone.egg-info/requires.txt
src/collective.megaphone.egg-info/top_level.txt
src/collective/megaphone/__init__.py
src/collective/megaphone/config.py
src/collective/megaphone/configure.zcml
src/collective/megaphone/constraints.py
src/collective/megaphone/initialize.py
src/collective/megaphone/interfaces.py
src/collective/megaphone/recipient_multiplexer.py
src/collective/megaphone/renderer.py
src/collective/megaphone/setuphandlers.py
src/collective/megaphone/utils.py
src/collective/megaphone/browser/__init__.py
src/collective/megaphone/browser/configure.zcml
src/collective/megaphone/browser/controlpanel.py
src/collective/megaphone/browser/crud_orderable_edit_form.pt
src/collective/megaphone/browser/crud_orderable_edit_subform.pt
src/collective/megaphone/browser/crud_orderable_form.pt
src/collective/megaphone/browser/descriptive_radio_input.pt
src/collective/megaphone/browser/fields_step.py
src/collective/megaphone/browser/general_step.py
src/collective/megaphone/browser/group_wizard_step.pt
src/collective/megaphone/browser/intro.pt
src/collective/megaphone/browser/megaphone.py
src/collective/megaphone/browser/popup_form.pt
src/collective/megaphone/browser/recipient_multiplexer.py
src/collective/megaphone/browser/recipients_step.pt
src/collective/megaphone/browser/recipients_step.py
src/collective/megaphone/browser/salesforce_step.py
src/collective/megaphone/browser/signers_listing.pt
src/collective/megaphone/browser/signers_listing.py
src/collective/megaphone/browser/signers_step.py
src/collective/megaphone/browser/summary.pt
src/collective/megaphone/browser/summary.py
src/collective/megaphone/browser/template_step.pt
src/collective/megaphone/browser/template_step.py
src/collective/megaphone/browser/thankyou_step.py
src/collective/megaphone/browser/utils.py
src/collective/megaphone/content/__init__.py
