Metadata-Version: 1.0
Name: collective.megaphone
Version: 2.1.4
Summary: Run an online advocacy campaign from your Plone site.
Home-page: http://svn.plone.org/svn/collective/collective.megaphone/trunk
Author: Groundwire
Author-email: davidglick@groundwire.org
License: GPL
Keywords: plone advocacy action letter petition
Platform: UNKNOWN
Classifier: Framework :: Plone
Classifier: Development Status :: 5 - Production/Stable
